argparse_best_practice/__init__.py
argparse_best_practice/__main__.py
argparse_best_practice/bool.py
argparse_best_practice/list.py
argparse_best_practice/number.py
argparse_best_practice/string.py
argparse_best_practice-0.1.3.dist-info/LICENSE
argparse_best_practice-0.1.3.dist-info/METADATA
argparse_best_practice-0.1.3.dist-info/WHEEL
argparse_best_practice-0.1.3.dist-info/top_level.txt
argparse_best_practice-0.1.3.dist-info/RECORD
