Metadata-Version: 2.1
Name: argparse-best-practice
Version: 0.1.3
Summary: python argparse best practice.
Home-page: https://github.com/oneofthezombies/argparse-best-practice
Author: oneofthezombies
Author-email: hunhoekim@gmail.com
License: MIT
Platform: UNKNOWN
Classifier: Programming Language :: Python :: 3
Classifier: License :: OSI Approved :: MIT License
Classifier: Operating System :: OS Independent
